{
  "hash": "1b7c166a2165180ecad64480cf51355d",
  "result": {
    "engine": "knitr",
    "markdown": "---\ntitle: \"Dot product\"\ndescription: \"Centered Kernel Alignment similarity between multiple representations.\"\nsidebar: api\ntoc: true\ncategories: [\"Core metrics\"] \nbibliography: REFERENCES.bib    # path relative to this file\nlink-citations: true               # hyperlink in-text cites to refs\n---\n\n\n\n\n\nDot-product similarity between multiple representations (Kornblith et al., 2019). test with [@kornblith_2019_SimilarityNeuralNetwork]\n\n::: {.panel-tabset}\n## Python\n\n**Function:** `repsim.dot_product(mats)`\n\n### Parameters\n- **mats**: list or tuple of M arrays, each with shape `(n_samples, n_features_k)`.  \n  All arrays must have the same number of rows (samples).\n\n### Returns\n- **ndarray** of shape `(M, M)` — symmetric matrix of pairwise dot-product similarities.\n\n### Example\n\n\n::: {.cell}\n\n```{.python .cell-code}\nimport numpy as np, repsim as rs\nX1, X2 = np.random.randn(100, 32), np.random.randn(100, 64)\nrs.dot_product([X1, X2])\n```\n\n::: {.cell-output .cell-output-stdout}\n\n```\narray([[ 432601.61160022,  202079.88167048],\n       [ 202079.88167048, 1038173.35738838]])\n```\n\n\n:::\n:::\n\n\n---\n\n## R\n\n**Function:** `dot_product(mats)`\n\n\n### Parameters\n- **mats**: list of M numeric matrices, each with dimension `(n_samples, n_features_k)` and identical row counts.\n\n### Returns\n- **matrix** of size `(M,M)` containing pairwise dot-product similarities.\n\n\n### Example\n\n::: {.cell}\n\n```{.r .cell-code}\nlibrary(repsim)\nset.seed(42)\nX1 <- matrix(rnorm(100*32), 100, 32)\nX2 <- matrix(rnorm(100*64), 100, 64)\ndot_product(list(X1, X2))\n```\n\n::: {.cell-output .cell-output-stdout}\n\n```\n         [,1]      [,2]\n[1,] 426171.1  223632.5\n[2,] 223632.5 1097888.1\n```\n\n\n:::\n:::\n\n:::\n\n### References\n::: {#refs}\n:::",
    "supporting": [],
    "filters": [
      "rmarkdown/pagebreak.lua"
    ],
    "includes": {},
    "engineDependencies": {},
    "preserve": {},
    "postProcess": true
  }
}